FuncHub/Common.py
FuncHub/__init__.py
FuncHub-0.1.6.dist-info/LICENSE
FuncHub-0.1.6.dist-info/METADATA
FuncHub-0.1.6.dist-info/WHEEL
FuncHub-0.1.6.dist-info/top_level.txt
FuncHub-0.1.6.dist-info/RECORD
